{"type":"PR","pr":{"number":51,"head":"82fdf8afd97c92bccc85c1429a951a2c4475f2f8"},"user":"T K Sudharshan","status":"draft","branch":"cms/2019-09-06-huawei’s-new-kirin-990-is-the-world’s-first-5g-integrated-chipset","collection":"posts","title":"Huawei’s new Kirin 990 is the world’s first 5G-integrated chipset","description":"Huawei has unveiled the Kirin 990 chipset at IFA 2019 in Berlin. The Kirin 990 is the world’s first 5G-integrated mobile chipset.","objects":{"entry":{"path":"_posts/2019-09-06-huawei’s-new-kirin-990-is-the-world’s-first-5g-integrated-chipset.md","sha":"d2bf95405feacc223f092c22a9318dabcb140a62"},"files":[]},"timeStamp":"2019-09-07T14:06:09.589Z"}